sphinx_nervproject_theme/__init__.py
sphinx_nervproject_theme/about.html
sphinx_nervproject_theme/domainindex.html
sphinx_nervproject_theme/genindex.html
sphinx_nervproject_theme/layout.html
sphinx_nervproject_theme/search.html
sphinx_nervproject_theme/share.html
sphinx_nervproject_theme/social.html
sphinx_nervproject_theme/theme.conf
sphinx_nervproject_theme/locale/sphinx.pot
sphinx_nervproject_theme/locale/en/LC_MESSAGES/sphinx.mo
sphinx_nervproject_theme/locale/en/LC_MESSAGES/sphinx.po
sphinx_nervproject_theme/locale/fr/LC_MESSAGES/sphinx.mo
sphinx_nervproject_theme/locale/fr/LC_MESSAGES/sphinx.po
sphinx_nervproject_theme/static/isso.css
sphinx_nervproject_theme/static/sphinx_nervproject_theme.js
sphinx_nervproject_theme/static/theme-dark-hc.css
sphinx_nervproject_theme/static/theme-dark.css
sphinx_nervproject_theme/static/theme-light-hc.css
sphinx_nervproject_theme/static/theme-light.css
sphinx_nervproject_theme/static/theme-print.css
sphinx_nervproject_theme/static/theme.css
sphinx_nervproject_theme/static/fa/brands.svg
sphinx_nervproject_theme/static/fa/regular.svg
sphinx_nervproject_theme/static/fa/solid.svg
sphinx_nervproject_theme/static/fonts/hack/Hack-Bold.woff
sphinx_nervproject_theme/static/fonts/hack/Hack-BoldItalic.woff
sphinx_nervproject_theme/static/fonts/hack/Hack-Italic.woff
sphinx_nervproject_theme/static/fonts/hack/Hack-Regular.woff
sphinx_nervproject_theme/static/fonts/luciole/Luciole-Bold-Italic.woff
sphinx_nervproject_theme/static/fonts/luciole/Luciole-Bold.woff
sphinx_nervproject_theme/static/fonts/luciole/Luciole-Regular-Italic.woff
sphinx_nervproject_theme/static/fonts/luciole/Luciole-Regular.woff
sphinx_nervproject_theme/util/bodyheader.html
sphinx_nervproject_theme/util/disqus.html
sphinx_nervproject_theme/util/extlinks.html
sphinx_nervproject_theme/util/fathom.html
sphinx_nervproject_theme/util/footer.html
sphinx_nervproject_theme/util/linktags.html
sphinx_nervproject_theme/util/navbar.html
sphinx_nervproject_theme/util/navlinks.html
sphinx_nervproject_theme-3.0.3.dist-info/entry_points.txt
sphinx_nervproject_theme-3.0.3.dist-info/LICENSE
sphinx_nervproject_theme-3.0.3.dist-info/LICENSE-de
sphinx_nervproject_theme-3.0.3.dist-info/LICENSE-fr
sphinx_nervproject_theme-3.0.3.dist-info/LICENSE-nl
sphinx_nervproject_theme-3.0.3.dist-info/LICENSE_FOR_FONTAWESOME.txt
sphinx_nervproject_theme-3.0.3.dist-info/WHEEL
sphinx_nervproject_theme-3.0.3.dist-info/METADATA
sphinx_nervproject_theme-3.0.3.dist-info/RECORD
