Metadata-Version: 2.1
Name: sphinx_nervproject_theme
Version: 3.0.3
Summary: A Sphinx-doc theme based on     Vuepress
Keywords: sphinx,doc,theme
Author: kujiu, ptitgnu
Author-email: Nerv Project ASBL <contact@nerv-project.eu>
Maintainer: kujiu, ptitgnu
Maintainer-email: Nerv Project ASBL <contact@nerv-project.eu>
Requires-Python: >=3.8
Classifier: Framework :: Sphinx
Classifier: Framework :: Sphinx :: Theme
Classifier: Development Status :: 5 - Production/Stable
Classifier: License :: OSI Approved :: European Union Public Licence 1.2 (EUPL 1.2)
Classifier: Environment :: Console
Classifier: Environment :: Web Environment
Classifier: Framework :: Sphinx :: Theme
Classifier: Intended Audience :: Developers
Classifier: Programming Language :: Python :: 3
Classifier: Operating System :: OS Independent
Classifier: Topic :: Documentation
Classifier: Topic :: Software Development :: Documentation
Requires-Dist: Sphinx>=7.0.0
Requires-Dist: reportlab
Requires-Dist: sphinx-fasvg
Requires-Dist: ablog>=0.11
Requires-Dist: Sphinx ; extra == "setup"
Requires-Dist: pytest-runner ; extra == "setup"
Requires-Dist: flake8 ; extra == "setup"
Requires-Dist: pylint ; extra == "setup"
Requires-Dist: babel ; extra == "setup"
Requires-Dist: flit ; extra == "setup"
Requires-Dist: pytest ; extra == "tests"
Requires-Dist: flake8 ; extra == "tests"
Requires-Dist: pylint ; extra == "tests"
Requires-Dist: pytest-cov ; extra == "tests"
Project-URL: changelog, https://procrastinator.nerv-project.eu/nerv-project/sphinx_nervproject_theme/raw/branch/main/CHANGES.rst
Project-URL: editor, https://www.nerv-project.eu
Project-URL: homepage, https://www.nerv-project.eu
Project-URL: issues, https://procrastinator.nerv-project.eu/nerv-project/sphinx_nervproject_theme/issues
Project-URL: repository, https://procrastinator.nerv-project.eu/nerv-project/sphinx_nervproject_theme
Provides-Extra: setup
Provides-Extra: tests
